{
  "AWSTemplateFormatVersion": "2010-09-09",
  "Description": "The AWS CloudFormation template for this Serverless application",
  "Resources": {
    "ServerlessDeploymentBucket": {
      "Type": "AWS::S3::Bucket",
      "Properties": {
        "BucketEncryption": {
          "ServerSideEncryptionConfiguration": [
            {
              "ServerSideEncryptionByDefault": {
                "SSEAlgorithm": "AES256"
              }
            }
          ]
        }
      }
    },
    "ServerlessDeploymentBucketPolicy": {
      "Type": "AWS::S3::BucketPolicy",
      "Properties": {
        "Bucket": {
          "Ref": "ServerlessDeploymentBucket"
        },
        "PolicyDocument": {
          "Statement": [
            {
              "Action": "s3:*",
              "Effect": "Deny",
              "Principal": "*",
              "Resource": [
                {
                  "Fn::Join": [
                    "",
                    [
                      "arn:",
                      {
                        "Ref": "AWS::Partition"
                      },
                      ":s3:::",
                      {
                        "Ref": "ServerlessDeploymentBucket"
                      },
                      "/*"
                    ]
                  ]
                },
                {
                  "Fn::Join": [
                    "",
                    [
                      "arn:",
                      {
                        "Ref": "AWS::Partition"
                      },
                      ":s3:::",
                      {
                        "Ref": "ServerlessDeploymentBucket"
                      }
                    ]
                  ]
                }
              ],
              "Condition": {
                "Bool": {
                  "aws:SecureTransport": false
                }
              }
            }
          ]
        }
      }
    },
    "SourceLogGroup": {
      "Type": "AWS::Logs::LogGroup",
      "Properties": {
        "LogGroupName": "/aws/lambda/web-app-123-stage, 'dev'-source"
      }
    },
    "IamRoleLambdaExecution": {
      "Type": "AWS::IAM::Role",
      "Properties": {
        "AssumeRolePolicyDocument": {
          "Version": "2012-10-17",
          "Statement": [
            {
              "Effect": "Allow",
              "Principal": {
                "Service": [
                  "lambda.amazonaws.com"
                ]
              },
              "Action": [
                "sts:AssumeRole"
              ]
            }
          ]
        },
        "Policies": [
          {
            "PolicyName": {
              "Fn::Join": [
                "-",
                [
                  "web-app-123",
                  "stage, 'dev'",
                  "lambda"
                ]
              ]
            },
            "PolicyDocument": {
              "Version": "2012-10-17",
              "Statement": [
                {
                  "Effect": "Allow",
                  "Action": [
                    "logs:CreateLogStream",
                    "logs:CreateLogGroup",
                    "logs:TagResource"
                  ],
                  "Resource": [
                    {
                      "Fn::Sub": "arn:${AWS::Partition}:logs:${AWS::Region}:${AWS::AccountId}:log-group:/aws/lambda/web-app-123-stage, 'dev'*:*"
                    }
                  ]
                },
                {
                  "Effect": "Allow",
                  "Action": [
                    "logs:PutLogEvents"
                  ],
                  "Resource": [
                    {
                      "Fn::Sub": "arn:${AWS::Partition}:logs:${AWS::Region}:${AWS::AccountId}:log-group:/aws/lambda/web-app-123-stage, 'dev'*:*:*"
                    }
                  ]
                }
              ]
            }
          }
        ],
        "Path": "/",
        "RoleName": {
          "Fn::Join": [
            "-",
            [
              "web-app-123",
              "stage, 'dev'",
              {
                "Ref": "AWS::Region"
              },
              "lambdaRole"
            ]
          ]
        }
      }
    },
    "SourceLambdaFunction": {
      "Type": "AWS::Lambda::Function",
      "Properties": {
        "Code": {
          "S3Bucket": {
            "Ref": "ServerlessDeploymentBucket"
          },
          "S3Key": "serverless/web-app-123/stage, 'dev'/1700413132505-2023-11-19T16:58:52.505Z/web-app-123.zip"
        },
        "Handler": "source.handler",
        "Runtime": "nodejs10.x",
        "FunctionName": "web-app-123-stage, 'dev'-source",
        "MemorySize": 128,
        "Timeout": 3,
        "Description": "function description",
        "Role": {
          "Fn::GetAtt": [
            "IamRoleLambdaExecution",
            "Arn"
          ]
        }
      },
      "DependsOn": [
        "SourceLogGroup"
      ]
    },
    "SourceLambdaVersionpEGLxwsF6JYufAZ1qt8BhyjTqyqJK9f4lMWQ58u7Fw": {
      "Type": "AWS::Lambda::Version",
      "DeletionPolicy": "Retain",
      "Properties": {
        "FunctionName": {
          "Ref": "SourceLambdaFunction"
        },
        "CodeSha256": "ylGI0Dk1TF+JvsQAT/prsHqO0OffhZTdN77SZ99CTnE=",
        "Description": "function description"
      }
    }
  },
  "Outputs": {
    "ServerlessDeploymentBucketName": {
      "Value": {
        "Ref": "ServerlessDeploymentBucket"
      },
      "Export": {
        "Name": "sls-web-app-123-stage, 'dev'-ServerlessDeploymentBucketName"
      }
    },
    "SourceLambdaFunctionQualifiedArn": {
      "Description": "Current Lambda function version",
      "Value": {
        "Ref": "SourceLambdaVersionpEGLxwsF6JYufAZ1qt8BhyjTqyqJK9f4lMWQ58u7Fw"
      },
      "Export": {
        "Name": "sls-web-app-123-stage, 'dev'-SourceLambdaFunctionQualifiedArn"
      }
    }
  }
}